bleumi_pay/__init__.py
bleumi_pay/api_client.py
bleumi_pay/configuration.py
bleumi_pay/rest.py
bleumi_pay/api/__init__.py
bleumi_pay/api/hosted_checkouts_api.py
bleumi_pay/api/payments_api.py
bleumi_pay/api/payouts_api.py
bleumi_pay/api/request_validator.py
bleumi_pay/models/__init__.py
bleumi_pay/models/algorand_address.py
bleumi_pay/models/algorand_balance.py
bleumi_pay/models/algorand_wallet_address.py
bleumi_pay/models/algorand_wallet_inputs.py
bleumi_pay/models/bad_request.py
bleumi_pay/models/chain.py
bleumi_pay/models/checkout_token.py
bleumi_pay/models/create_checkout_url_request.py
bleumi_pay/models/create_checkout_url_response.py
bleumi_pay/models/create_payout_request.py
bleumi_pay/models/create_payout_response.py
bleumi_pay/models/ethereum_address.py
bleumi_pay/models/ethereum_balance.py
bleumi_pay/models/ethereum_wallet_address.py
bleumi_pay/models/ethereum_wallet_inputs.py
bleumi_pay/models/paginated_payment_operations.py
bleumi_pay/models/paginated_payments.py
bleumi_pay/models/paginated_payout_items.py
bleumi_pay/models/payment.py
bleumi_pay/models/payment_addresses.py
bleumi_pay/models/payment_balances.py
bleumi_pay/models/payment_operation.py
bleumi_pay/models/payment_operation_inputs.py
bleumi_pay/models/payment_operation_response.py
bleumi_pay/models/payment_refund_request.py
bleumi_pay/models/payment_settle_request.py
bleumi_pay/models/payout.py
bleumi_pay/models/payout_item.py
bleumi_pay/models/payout_item_inputs.py
bleumi_pay/models/rsk_address.py
bleumi_pay/models/rsk_balance.py
bleumi_pay/models/validate_checkout_request.py
bleumi_pay/models/validate_checkout_response.py
bleumi_pay/models/wallet_balance.py
bleumi_pay-1.0.9.dist-info/LICENSE
bleumi_pay-1.0.9.dist-info/METADATA
bleumi_pay-1.0.9.dist-info/WHEEL
bleumi_pay-1.0.9.dist-info/top_level.txt
bleumi_pay-1.0.9.dist-info/RECORD
