Metadata-Version: 2.1
Name: bleumi-pay
Version: 1.0.9
Summary: Bleumi Pay API
Home-page: https://bleumi.com/
Author-email: karthic.krisnakumar@bleumi.com
License: UNKNOWN
Keywords: payment-gateway,digital-currency-payments,accept-digital-currency-payments,payment-processing,stable-coins,ethereum,erc20-tokens,algorand-standard-assets,algorand,xDai,bitcoin,rsk,rsk erc-20 tokens,Bleumi Pay API
Platform: UNKNOWN
Requires-Dist: urllib3 (>=1.15)
Requires-Dist: six (>=1.10)
Requires-Dist: certifi
Requires-Dist: python-dateutil
